[
  {
    "model": "budgetportal.video",
    "pk": 1,
    "fields": {
      "title_id": "onlineBudgetPortal",
      "title": "About the Online Budget Data Portal project",
      "description": "Learn more about the new Online Budget Data Portal that is being built to help you understand the country's finances in a simple way."
    }
  },
  {
    "model": "budgetportal.video",
    "pk": 2,
    "fields": {
      "title_id": "whyBudgetIsImportant",
      "title": "Why the budget is important to all South Africans",
      "description": "Find out why the national budget is important to all South Africans, and how vulekamali.gov.za can help you explore and understand the budget."
    }
  },
  {
    "model": "budgetportal.video",
    "pk": 3,
    "fields": {
      "title_id": "howCanTheBudgetPortalHelpYou",
      "title": "How can the budget portal help you?",
      "description": "Follow Xholiswa as she explores the budget and helps to bring change to her childhood school. Learn how understanding budgets can help you understand who is responsible for service delivery."
    }
  },
  {
    "model": "budgetportal.video",
    "pk": 4,
    "fields": {
      "title_id": "theBudgetProcess",
      "title": "The budget process",
      "description": "Interested in finding out how the South African budget process works? Learn about the budget process, how it relates to our constitution and the role that it plays in a modern day democracy."
    }
  },
  {
    "model": "budgetportal.video",
    "pk": 5,
    "fields": {
      "title_id": "participate",
      "title": "How to participate in the budget process?",
      "description": "The South African Constitution has several provisions that support people\u2019s participation in areas of democratic governance. One such area of participation is in the allocation of funding by mean of the national budget."
    }
  },
  {
    "model": "budgetportal.videolanguage",
    "pk": 1,
    "fields": {
      "label": "English",
      "youtube_id": "zFalZt862hk",
      "video": 1
    }
  },
  {
    "model": "budgetportal.videolanguage",
    "pk": 2,
    "fields": {
      "label": "Afrikaans",
      "youtube_id": "jsT2YFRDETk",
      "video": 1
    }
  },
  {
    "model": "budgetportal.videolanguage",
    "pk": 3,
    "fields": {
      "label": "isiZulu",
      "youtube_id": "lMUqzosN6ck",
      "video": 1
    }
  },
  {
    "model": "budgetportal.videolanguage",
    "pk": 4,
    "fields": {
      "label": "isiXhosa",
      "youtube_id": "nHUDu2SJ9DQ",
      "video": 1
    }
  },
  {
    "model": "budgetportal.videolanguage",
    "pk": 5,
    "fields": {
      "label": "Sesotho",
      "youtube_id": "lUbcKHxnGkI",
      "video": 1
    }
  },
  {
    "model": "budgetportal.videolanguage",
    "pk": 6,
    "fields": {
      "label": "English",
      "youtube_id": "KwNr4_0md4k",
      "video": 2
    }
  },
  {
    "model": "budgetportal.videolanguage",
    "pk": 7,
    "fields": {
      "label": "Afrikaans",
      "youtube_id": "rl8Qagr4UnU",
      "video": 2
    }
  },
  {
    "model": "budgetportal.videolanguage",
    "pk": 8,
    "fields": {
      "label": "isiZulu",
      "youtube_id": "VTt7mhJTdKI",
      "video": 2
    }
  },
  {
    "model": "budgetportal.videolanguage",
    "pk": 9,
    "fields": {
      "label": "isiXhosa",
      "youtube_id": "g6II7LrWgwk",
      "video": 2
    }
  },
  {
    "model": "budgetportal.videolanguage",
    "pk": 10,
    "fields": {
      "label": "Sesotho",
      "youtube_id": "0113dqpYQD4",
      "video": 2
    }
  },
  {
    "model": "budgetportal.videolanguage",
    "pk": 11,
    "fields": {
      "label": "English",
      "youtube_id": "wnsso3MgvEw",
      "video": 3
    }
  },
  {
    "model": "budgetportal.videolanguage",
    "pk": 12,
    "fields": {
      "label": "Afrikaans",
      "youtube_id": "XKq0SeLlkNU",
      "video": 3
    }
  },
  {
    "model": "budgetportal.videolanguage",
    "pk": 13,
    "fields": {
      "label": "isiZulu",
      "youtube_id": "Kq_2_tskRRs",
      "video": 3
    }
  },
  {
    "model": "budgetportal.videolanguage",
    "pk": 14,
    "fields": {
      "label": "isiXhosa",
      "youtube_id": "Scex0GnDQRQ",
      "video": 3
    }
  },
  {
    "model": "budgetportal.videolanguage",
    "pk": 15,
    "fields": {
      "label": "Sesotho",
      "youtube_id": "eNR7szO1m0U",
      "video": 3
    }
  },
  {
    "model": "budgetportal.videolanguage",
    "pk": 16,
    "fields": {
      "label": "English",
      "youtube_id": "f8fkoWW33Gs",
      "video": 4
    }
  },
  {
    "model": "budgetportal.videolanguage",
    "pk": 17,
    "fields": {
      "label": "Afrikaans",
      "youtube_id": "iXq0l040KSI",
      "video": 4
    }
  },
  {
    "model": "budgetportal.videolanguage",
    "pk": 18,
    "fields": {
      "label": "isiZulu",
      "youtube_id": "bj0Ep5YfFEI",
      "video": 4
    }
  },
  {
    "model": "budgetportal.videolanguage",
    "pk": 19,
    "fields": {
      "label": "isiXhosa",
      "youtube_id": "cs0JLUGQ-jI",
      "video": 4
    }
  },
  {
    "model": "budgetportal.videolanguage",
    "pk": 20,
    "fields": {
      "label": "Sesotho",
      "youtube_id": "SmSPPJPdUEw",
      "video": 4
    }
  },
  {
    "model": "budgetportal.videolanguage",
    "pk": 21,
    "fields": {
      "label": "English",
      "youtube_id": "UdahlP28-ok",
      "video": 5
    }
  },
  {
    "model": "budgetportal.videolanguage",
    "pk": 22,
    "fields": {
      "label": "Afrikaans",
      "youtube_id": "izvIkGf4xuA",
      "video": 5
    }
  },
  {
    "model": "budgetportal.videolanguage",
    "pk": 23,
    "fields": {
      "label": "isiZulu",
      "youtube_id": "-TCm9XcczTk",
      "video": 5
    }
  },
  {
    "model": "budgetportal.videolanguage",
    "pk": 24,
    "fields": {
      "label": "isiXhosa",
      "youtube_id": "iH7JTKnN98s",
      "video": 5
    }
  },
  {
    "model": "budgetportal.videolanguage",
    "pk": 25,
    "fields": {
      "label": "Sesotho",
      "youtube_id": "ftN0mlhnuNA",
      "video": 5
    }
  }
]
